coveralls/__init__.py
coveralls/api.py
coveralls/control.py
coveralls/report.py
coveralls/repository.py
coveralls/tests.py
python_coveralls-2.9.2.dist-info/LICENSE
python_coveralls-2.9.2.dist-info/METADATA
python_coveralls-2.9.2.dist-info/WHEEL
python_coveralls-2.9.2.dist-info/entry_points.txt
python_coveralls-2.9.2.dist-info/top_level.txt
python_coveralls-2.9.2.dist-info/RECORD
