Metadata-Version: 1.1
Name: python-coveralls
Version: 2.9.2
Summary: Python interface to coveralls.io API
